[
  {
    "name": "citation",
    "title": "Citation",
    "options": [
      {
        "name": "abstract",
        "description": "Abstract of the item (e.g. the abstract of a journal article)"
      },
      {
        "name": "author",
        "description": "The author(s) of the item."
      },
      {
        "name": "doi",
        "description": "Digital Object Identifier (e.g. \"10.1128/AEM.02591-07\")"
      },
      {
        "name": "references",
        "description": "Resources related to the procedural history of a legal case or legislation;\n\nCan also be used to refer to the procedural history of other items (e.g. \n\"Conference canceled\" for a presentation accepted as a conference that was subsequently \ncanceled; details of a retraction or correction notice)\n"
      },
      {
        "name": "title",
        "description": "The primary title of the item."
      }
    ]
  }
]